{
  "data": {
    "rule": {
      "actions": [
        {
          "actionId": "hide",
          "id": "327051380",
          "phaseField": {
            "id": "desconto_no_valor_vari_vel_do_saas_para_hospedagem",
            "internal_id": "422909786",
            "label": "Valor percentual de desconto SaaS - Categoria  Hospedagem",
            "uuid": "14b1012b-be44-4b31-a678-ba4bd25537f4"
          },
          "phaseFieldId": "422909786",
          "whenEvaluator": true
        }
      ],
      "condition": {
        "expressions": [
          {
            "field_address": "422909779",
            "id": "315064158",
            "operation": "not_equals",
            "structure_id": "0",
            "value": "1260337139"
          }
        ],
        "expressions_structure": [
          [
            "0"
          ]
        ],
        "id": "312580003"
      },
      "id": "306382060",
      "name": "Tipo de desconto Hospedagem != Valor percentual",
      "url": "https://app.pipefy.com/pipes/306859915/settings/form/conditionals/306382060"
    }
  },
  "meta": {
    "pipe_id": "306859915",
    "rule_id": "306382060",
    "scope": "start_form"
  }
}