{
  "data": {
    "automation": {
      "__typename": "Automation",
      "action_id": "move_parent_card",
      "action_params": {
        "__typename": "AutomationActionParams",
        "authenticationAddTo": null,
        "authenticationKey": null,
        "authenticationType": null,
        "body": null,
        "card_id": null,
        "email_template_id": null,
        "field_map": null,
        "fields_map_order": null,
        "hasAuthenticationValue": false,
        "headers": null,
        "httpMethod": null,
        "strategy": null,
        "to_phase_id": "339455412",
        "url": null
      },
      "active": false,
      "condition": {
        "__typename": "Condition",
        "expressions": [],
        "expressions_structure": [],
        "id": "311118395"
      },
      "created_at": "2025-07-16 16:29:09 UTC",
      "event_id": "card_moved",
      "event_params": {
        "__typename": "AutomationEventParams",
        "fromPhaseId": null,
        "inPhaseId": null,
        "kindOfSla": null,
        "to_phase_id": "339069572",
        "triggerAutomationId": null,
        "triggerFieldIds": null
      },
      "id": "305250065",
      "name": "Mover card pai de onboarding para parametrização quando ambiente for criado",
      "url": "https://app.pipefy.com/pipes/306468093/settings/automations/305250065"
    }
  }
}