{
  "data": {
    "field": {
      "canConnectExisting": false,
      "canConnectMultiples": true,
      "canCreateNewConnected": true,
      "connectedRepo": null,
      "connected_repo": null,
      "description": "Indique aqui condições especiais de pagamento, início da cobrança a partir do mês X, etc.",
      "help": "",
      "id": "observa_es_da_negocia_o",
      "index": 97.875,
      "internal_id": "415395678",
      "label": "Observações da negociação",
      "options": [],
      "required": true,
      "type": "long_text",
      "uuid": "6544ac79-5885-459a-86a1-0806be176bd1"
    }
  },
  "meta": {
    "field_id": "observa_es_da_negocia_o",
    "phase": {
      "id": "338732673",
      "name": "Oportunidade em negociação",
      "uuid": "0c28859c-0511-4ee3-9d05-c8fb487ae7cb"
    },
    "pipe_id": "306411209",
    "scope": "phase"
  }
}