{
  "data": {
    "rule": {
      "actions": [
        {
          "actionId": "hide",
          "id": "327048693",
          "phaseField": {
            "id": "desconto_no_valor_vari_vel_do_saas_para_a_b",
            "internal_id": "422751359",
            "label": "Valor percentual de desconto SaaS - Categoria A&B",
            "uuid": "2aa4d950-f945-4a92-8482-0e1601a7ffe1"
          },
          "phaseFieldId": "422751359",
          "whenEvaluator": true
        }
      ],
      "condition": {
        "expressions": [
          {
            "field_address": "422751354",
            "id": "315062483",
            "operation": "not_equals",
            "structure_id": "0",
            "value": "1260337139"
          }
        ],
        "expressions_structure": [
          [
            "0"
          ]
        ],
        "id": "312578341"
      },
      "id": "306381445",
      "name": "Tipo de desconto A&B != Valor percentual",
      "url": "https://app.pipefy.com/pipes/306852209/settings/form/conditionals/306381445"
    }
  },
  "meta": {
    "pipe_id": "306852209",
    "rule_id": "306381445",
    "scope": "start_form"
  }
}