{
  "data": {
    "field": {
      "canConnectExisting": false,
      "canConnectMultiples": true,
      "canCreateNewConnected": true,
      "connectedRepo": null,
      "connected_repo": null,
      "description": "",
      "help": "",
      "id": "observa_es_da_ficha_cadastral",
      "internal_id": "419458320",
      "label": "Observações da ficha cadastral",
      "options": [],
      "required": false,
      "type": "long_text",
      "uuid": "bdce7e17-32d7-4a41-a3fb-eaffea49ca82"
    }
  },
  "meta": {
    "field_id": "observa_es_da_ficha_cadastral",
    "pipe_id": "306500191",
    "scope": "start_form"
  }
}